<?xml version="1.0" encoding="UTF-8"?>
<metadata xml:lang="pt"><Esri><CreaDate>20190609</CreaDate><CreaTime>09381600</CreaTime><ArcGISFormat>1.0</ArcGISFormat><SyncOnce>TRUE</SyncOnce><DataProperties><lineage><Process ToolSource="c:\program files (x86)\arcgis\desktop10.5\ArcToolbox\Toolboxes\Data Management Tools.tbx\CalculateField" Date="20190609" Time="093816">CalculateField MG_Municipio_2018 Datum_Orig 'SIRGAS 2000' PYTHON_9.3 #</Process><Process ToolSource="c:\program files (x86)\arcgis\desktop10.5\ArcToolbox\Toolboxes\Data Management Tools.tbx\CalculateField" Date="20190609" Time="093917">CalculateField MG_Municipio_2018 Datum_Atua 'WGS84' PYTHON_9.3 #</Process></lineage></DataProperties></Esri></metadata>
